{
  "_fv": 43,
  "_type": "recipe",
  "definition": {
    "recipeType": "Crafting",
    "recipeRetstackSize": 1,
    "group": "portal_frames",
    "cookingBookCategory": "MISC",
    "xpReward": 0.0,
    "cookingTime": 200,
    "craftingBookCategory": "MISC",
    "recipeShapeless": true,
    "recipeSlots": [
      {
        "value": "CUSTOM:BrokenPortalFrame"
      },
      {
        "value": "CUSTOM:BrokenPortalFrame"
      },
      {
        "value": "CUSTOM:BrokenPortalFrame"
      },
      {
        "value": ""
      },
      {
        "value": "CUSTOM:HeartofOverworld"
      },
      {
        "value": ""
      },
      {
        "value": ""
      },
      {
        "value": ""
      },
      {
        "value": ""
      }
    ],
    "recipeReturnStack": {
      "value": "CUSTOM:OverworldIgniter"
    },
    "name": "overworld_portal_frame",
    "namespace": "mod"
  }
}