{
  "_fv": 43,
  "_type": "loottable",
  "definition": {
    "type": "Block",
    "pools": [
      {
        "minrolls": 1,
        "maxrolls": 3,
        "minbonusrolls": 1,
        "maxbonusrolls": 2,
        "hasbonusrolls": true,
        "entries": [
          {
            "type": "item",
            "item": {
              "value": "Blocks.REDSTONE_ORE"
            },
            "weight": 3,
            "minCount": 2,
            "maxCount": 6,
            "minEnchantmentLevel": 0,
            "maxEnchantmentLevel": 0,
            "affectedByFortune": false,
            "explosionDecay": false,
            "silkTouchMode": 2
          },
          {
            "type": "item",
            "item": {
              "value": "Blocks.COAL_ORE"
            },
            "weight": 4,
            "minCount": 2,
            "maxCount": 6,
            "minEnchantmentLevel": 0,
            "maxEnchantmentLevel": 0,
            "affectedByFortune": false,
            "explosionDecay": false,
            "silkTouchMode": 2
          },
          {
            "type": "item",
            "item": {
              "value": "Blocks.EMERALD_ORE"
            },
            "weight": 2,
            "minCount": 1,
            "maxCount": 3,
            "minEnchantmentLevel": 0,
            "maxEnchantmentLevel": 0,
            "affectedByFortune": false,
            "explosionDecay": false,
            "silkTouchMode": 2
          },
          {
            "type": "item",
            "item": {
              "value": "Blocks.DIAMOND_ORE"
            },
            "weight": 2,
            "minCount": 2,
            "maxCount": 5,
            "minEnchantmentLevel": 0,
            "maxEnchantmentLevel": 0,
            "affectedByFortune": false,
            "explosionDecay": false,
            "silkTouchMode": 2
          },
          {
            "type": "item",
            "item": {
              "value": "CUSTOM:LushtOre"
            },
            "weight": 4,
            "minCount": 3,
            "maxCount": 12,
            "minEnchantmentLevel": 0,
            "maxEnchantmentLevel": 0,
            "affectedByFortune": false,
            "explosionDecay": false,
            "silkTouchMode": 2
          },
          {
            "type": "item",
            "item": {
              "value": "Blocks.COPPER_ORE"
            },
            "weight": 2,
            "minCount": 2,
            "maxCount": 4,
            "minEnchantmentLevel": 0,
            "maxEnchantmentLevel": 0,
            "affectedByFortune": false,
            "explosionDecay": false,
            "silkTouchMode": 2
          },
          {
            "type": "item",
            "item": {
              "value": "Items.EMERALD"
            },
            "weight": 2,
            "minCount": 3,
            "maxCount": 9,
            "minEnchantmentLevel": 0,
            "maxEnchantmentLevel": 0,
            "affectedByFortune": false,
            "explosionDecay": false,
            "silkTouchMode": 1
          },
          {
            "type": "item",
            "item": {
              "value": "Items.DIAMOND"
            },
            "weight": 2,
            "minCount": 2,
            "maxCount": 6,
            "minEnchantmentLevel": 0,
            "maxEnchantmentLevel": 0,
            "affectedByFortune": false,
            "explosionDecay": false,
            "silkTouchMode": 1
          },
          {
            "type": "item",
            "item": {
              "value": "CUSTOM:LushtDust"
            },
            "weight": 2,
            "minCount": 3,
            "maxCount": 9,
            "minEnchantmentLevel": 0,
            "maxEnchantmentLevel": 0,
            "affectedByFortune": false,
            "explosionDecay": false,
            "silkTouchMode": 1
          },
          {
            "type": "item",
            "item": {
              "value": "Items.REDSTONE"
            },
            "weight": 2,
            "minCount": 3,
            "maxCount": 6,
            "minEnchantmentLevel": 0,
            "maxEnchantmentLevel": 0,
            "affectedByFortune": false,
            "explosionDecay": false,
            "silkTouchMode": 1
          },
          {
            "type": "item",
            "item": {
              "value": "Items.COPPER_INGOT"
            },
            "weight": 3,
            "minCount": 4,
            "maxCount": 9,
            "minEnchantmentLevel": 0,
            "maxEnchantmentLevel": 0,
            "affectedByFortune": false,
            "explosionDecay": false,
            "silkTouchMode": 1
          },
          {
            "type": "item",
            "item": {
              "value": "CUSTOM:RandomLootOres"
            },
            "weight": 1,
            "minCount": 1,
            "maxCount": 2,
            "minEnchantmentLevel": 0,
            "maxEnchantmentLevel": 0,
            "affectedByFortune": true,
            "explosionDecay": false,
            "silkTouchMode": 2
          },
          {
            "type": "item",
            "item": {
              "value": "CUSTOM:RandomLootOres"
            },
            "weight": 4,
            "minCount": 3,
            "maxCount": 6,
            "minEnchantmentLevel": 0,
            "maxEnchantmentLevel": 0,
            "affectedByFortune": true,
            "explosionDecay": false,
            "silkTouchMode": 1
          },
          {
            "type": "item",
            "item": {
              "value": "CUSTOM:HeartofNether"
            },
            "weight": 2,
            "minCount": 1,
            "maxCount": 2,
            "minEnchantmentLevel": 0,
            "maxEnchantmentLevel": 0,
            "affectedByFortune": true,
            "explosionDecay": true,
            "silkTouchMode": 0
          },
          {
            "type": "item",
            "item": {
              "value": "CUSTOM:NetherIgniter"
            },
            "weight": 1,
            "minCount": 1,
            "maxCount": 1,
            "minEnchantmentLevel": 0,
            "maxEnchantmentLevel": 0,
            "affectedByFortune": true,
            "explosionDecay": true,
            "silkTouchMode": 1
          },
          {
            "type": "item",
            "item": {
              "value": "CUSTOM:OverworldIgniter"
            },
            "weight": 1,
            "minCount": 1,
            "maxCount": 1,
            "minEnchantmentLevel": 0,
            "maxEnchantmentLevel": 0,
            "affectedByFortune": true,
            "explosionDecay": true,
            "silkTouchMode": 1
          },
          {
            "type": "item",
            "item": {
              "value": "CUSTOM:Dimension1Igniter"
            },
            "weight": 1,
            "minCount": 1,
            "maxCount": 1,
            "minEnchantmentLevel": 0,
            "maxEnchantmentLevel": 0,
            "affectedByFortune": true,
            "explosionDecay": true,
            "silkTouchMode": 1
          },
          {
            "type": "item",
            "item": {
              "value": "CUSTOM:HeartofOverworld"
            },
            "weight": 2,
            "minCount": 1,
            "maxCount": 1,
            "minEnchantmentLevel": 0,
            "maxEnchantmentLevel": 0,
            "affectedByFortune": true,
            "explosionDecay": true,
            "silkTouchMode": 0
          },
          {
            "type": "item",
            "item": {
              "value": "CUSTOM:HeartofFirstDimension"
            },
            "weight": 2,
            "minCount": 1,
            "maxCount": 1,
            "minEnchantmentLevel": 0,
            "maxEnchantmentLevel": 0,
            "affectedByFortune": true,
            "explosionDecay": true,
            "silkTouchMode": 0
          },
          {
            "type": "item",
            "item": {
              "value": "CUSTOM:BrokenPortalFrame"
            },
            "weight": 3,
            "minCount": 1,
            "maxCount": 1,
            "minEnchantmentLevel": 0,
            "maxEnchantmentLevel": 0,
            "affectedByFortune": true,
            "explosionDecay": true,
            "silkTouchMode": 0
          }
        ]
      }
    ],
    "name": "blocks/random_ores",
    "namespace": "mod"
  }
}